{
  "version": "1.0.0",
  "sources": [
    { "type": "docs", "url": "https://gitlab.com/es-de/emulationstation-de/", "last_reviewed": "2026-04-29", "confidence": "medium" },
    { "type": "docs", "url": "https://wiki.batocera.org/systems", "last_reviewed": "2026-04-29", "confidence": "medium" },
    { "type": "docs", "url": "https://emudeck.github.io/cheat-sheet/", "last_reviewed": "2026-04-29", "confidence": "medium" }
  ],
  "groups": [
    { "canonical": "jaguar", "aliases": ["atarijaguar"], "reason": "Atari Jaguar folders vary by frontend.", "status": "canonical_alias" },
    { "canonical": "jaguarcd", "aliases": ["atarijaguarcd"], "reason": "Atari Jaguar CD folders vary by frontend.", "status": "canonical_alias" },
    { "canonical": "astrocde", "aliases": ["astrocade"], "reason": "Bally Astrocade is commonly spelled as both astrocde and astrocade.", "status": "split_records" },
    { "canonical": "turbografx", "aliases": ["pcengine", "tg16"], "reason": "NEC HuCard folder names vary by region/frontend.", "status": "canonical_alias" },
    { "canonical": "genesis", "aliases": ["megadrive"], "reason": "Sega 16-bit folder names vary by region/frontend.", "status": "canonical_alias" },
    { "canonical": "zx-spectrum", "aliases": ["zxspectrum"], "reason": "ZX Spectrum folders may omit punctuation.", "status": "split_records" },
    { "canonical": "pico8", "aliases": ["pico"], "reason": "Some frontends shorten PICO-8 folder IDs to pico.", "status": "split_records" },
    { "canonical": "openbor", "aliases": ["ports"], "reason": "Ports folders are sometimes used as an OpenBOR or native-port bucket.", "status": "split_records" },
    { "canonical": "saturn", "aliases": ["saturnjp"], "reason": "Some frontends separate Japanese Saturn folders.", "status": "canonical_alias" },
    { "canonical": "sega32x", "aliases": ["sega32xjp"], "reason": "Some frontends separate Japanese 32X folders.", "status": "canonical_alias" },
    { "canonical": "sms", "aliases": ["mastersystem"], "reason": "Sega Master System folders may use abbreviation or full name.", "status": "canonical_alias" },
    { "canonical": "ds", "aliases": ["nds"], "reason": "Nintendo DS folders may include the Nintendo prefix.", "status": "canonical_alias" },
    { "canonical": "3ds", "aliases": ["n3ds"], "reason": "Nintendo 3DS folders may include the Nintendo prefix.", "status": "canonical_alias" },
    { "canonical": "snes", "aliases": ["sfc"], "reason": "SNES/Super Famicom folder IDs vary by region/frontend.", "status": "canonical_alias" },
    { "canonical": "odyssey2", "aliases": ["videopac"], "reason": "Magnavox Odyssey 2 and Philips Videopac names vary by region.", "status": "canonical_alias" },
    { "canonical": "wonderswan", "aliases": ["wswan", "wonderswancolor"], "reason": "WonderSwan folders often split monochrome/color or abbreviate names.", "status": "canonical_alias" }
  ]
}
